{
  "annotations": { "list": [] },
  "editable": true,
  "fiscalYearStartMonth": 0,
  "graphTooltip": 0,
  "id": null,
  "links": [],
  "panels": [
    {
      "datasource": { "type": "loki", "uid": "loki" },
      "fieldConfig": { "defaults": {}, "overrides": [] },
      "gridPos": { "h": 4, "w": 24, "x": 0, "y": 0 },
      "id": 10,
      "options": {
        "colorMode": "background",
        "graphMode": "none",
        "justifyMode": "center",
        "orientation": "horizontal",
        "reduceOptions": { "calcs": ["count"], "fields": "", "values": false },
        "textMode": "auto"
      },
      "targets": [
        {
          "datasource": { "type": "loki", "uid": "loki" },
          "expr": "count_over_time({app=\"petgym\", level=\"ERROR\"}[$__range])",
          "instant": true,
          "legendFormat": "Ошибок",
          "refId": "A"
        },
        {
          "datasource": { "type": "loki", "uid": "loki" },
          "expr": "count_over_time({app=\"petgym\", level=\"WARN\"}[$__range])",
          "instant": true,
          "legendFormat": "Предупреждений",
          "refId": "B"
        }
      ],
      "title": "Статистика за период",
      "type": "stat"
    },
    {
      "datasource": { "type": "loki", "uid": "loki" },
      "fieldConfig": { "defaults": {}, "overrides": [] },
      "gridPos": { "h": 8, "w": 24, "x": 0, "y": 4 },
      "id": 20,
      "options": {
        "bucketSize": "auto",
        "fillOpacity": 50,
        "gradientMode": "none",
        "legendDisplayMode": "list",
        "legendPlacement": "bottom",
        "lineWidth": 1
      },
      "targets": [
        {
          "datasource": { "type": "loki", "uid": "loki" },
          "expr": "sum by (level) (count_over_time({app=\"petgym\"} [$__interval]))",
          "legendFormat": "{{level}}",
          "refId": "A"
        }
      ],
      "title": "Частота логов по уровням",
      "type": "barchart"
    },
    {
      "datasource": { "type": "loki", "uid": "loki" },
      "fieldConfig": { "defaults": {}, "overrides": [] },
      "gridPos": { "h": 20, "w": 24, "x": 0, "y": 12 },
      "id": 30,
      "options": {
        "dedupStrategy": "none",
        "enableLogDetails": true,
        "prettifyLogMessage": false,
        "showCommonLabels": false,
        "showLabels": true,
        "showTime": true,
        "sortOrder": "Descending",
        "wrapLogMessage": true
      },
      "targets": [
        {
          "datasource": { "type": "loki", "uid": "loki" },
          "expr": "{app=\"petgym\"} |= \"$search\"",
          "legendFormat": "",
          "queryType": "range",
          "refId": "A"
        }
      ],
      "title": "Логи приложения",
      "type": "logs"
    }
  ],
  "refresh": "10s",
  "schemaVersion": 39,
  "tags": ["petgym", "logs"],
  "templating": {
    "list": [
      {
        "current": { "selected": false, "text": "", "value": "" },
        "hide": 0,
        "label": "Поиск",
        "name": "search",
        "options": [{ "selected": true, "text": "", "value": "" }],
        "query": "",
        "skipUrlSync": false,
        "type": "textbox"
      }
    ]
  },
  "time": { "from": "now-1h", "to": "now" },
  "timepicker": {},
  "timezone": "browser",
  "title": "Pet Gym — Логи",
  "uid": "petgym-logs",
  "version": 1
}
